{
  "title": "SchemaCrawler - Introduction",
  "description": "Introduction to the SchemaCrawler Command-line",
  "difficulty": "Beginner",
  "time": "5 minutes",
  "details": {
    "assets": {
        "client": [
            {"file": "tables.js", "target": "~/"}
        ]
    },
    "intro": {
      "code": "scripts/env-init.sh",
      "text": "intro.md"
    },
    "steps": [
      {
        "title": "Step 1 - Run SchemaCrawler from the Command-line",
        "text": "step1.md"
      },
      {
        "title": "Step 2 - Get a List of Tables",
        "text": "step2.md"
      },
      {
        "title": "Step 3 - Get Details of Tables",
        "text": "step3.md"
      },
      {
        "title": "Step 4 - Limit Tables in Output",
        "text": "step4.md"
      },
      {
        "title": "Step 5 - Search for Tables",
        "text": "step5.md"
      },
      {
        "title": "Step 6 - Run Other Commands",
        "text": "step6.md"
      },
      {
        "title": "Step 7 - Find Related Tables",
        "text": "step7.md"
      }
    ],
    "finish": {
      "text": "finish.md"
    }
  },
  "environment": {
    "uilayout": "terminal",
    "uimessage1": "\u001b[32mPlease wait for the SchemaCrawler Docker image to start...\u001b[m\r\n"
  },
  "backend": {
    "imageid": "ubuntu"
  }
}
